LICENSE
MANIFEST.in
README.md
setup.py
unlimitediplist/__init__.py
unlimitediplist/unlimitediplist.py
unlimitediplist/unlimitediplist_min.py
unlimitediplist.egg-info/PKG-INFO
unlimitediplist.egg-info/SOURCES.txt
unlimitediplist.egg-info/dependency_links.txt
unlimitediplist.egg-info/not-zip-safe
unlimitediplist.egg-info/top_level.txt