Metadata-Version: 2.4
Name: unlimitediplist
Version: 1.0.1
Summary: A list-type object to manage lists of IPv4/IPv6 networks and perform super-fast lookups of IPv4/IPv6 addresses within the networks in that list. A lookup takes around 0.000005 seconds regardless of the size of the list and it´s pure Python!
Home-page: https://github.com/rabuchaim/unlimitediplist
Author: Ricardo Abuchaim
Author-email: ricardoabuchaim@gmail.com
Maintainer: Ricardo Abuchaim
Maintainer-email: ricardoabuchaim@gmail.com
License: MIT
Project-URL: Issue Tracker, https://github.com/rabuchaim/unlimitediplist/issues
Project-URL: Source code, https://github.com/rabuchaim/unlimitediplist
Keywords: iplist,unlimited_ip_list,accesslimit,accesslimiter,ratelimit,ratelimiter,fastratelimiter,api,rate limit,firewall,blocking,flask,tornado,fastapi,bottle,purepython,pure,rules,tools
Classifier: Development Status :: 5 - Production/Stable
Classifier: Intended Audience :: Developers
Classifier: License :: OSI Approved :: MIT License
Classifier: Programming Language :: Python :: 3
Classifier: Programming Language :: Python :: 3.10
Classifier: Operating System :: OS Independent
Classifier: Topic :: Internet
Classifier: Topic :: Security
Classifier: Topic :: Software Development :: Libraries :: Python Modules
Requires-Python: >=3.10
License-File: LICENSE
Dynamic: author
Dynamic: author-email
Dynamic: classifier
Dynamic: description
Dynamic: description-content-type
Dynamic: home-page
Dynamic: keywords
Dynamic: license
Dynamic: license-file
Dynamic: maintainer
Dynamic: maintainer-email
Dynamic: project-url
Dynamic: requires-python
Dynamic: summary
